__init__.py
ezwifi.py
test.py
test2.py
ezwlan/__init__.py
ezwlan/ezwlan.py
ezwlan/wlanapi.py
ezwifi-1.0.0.11.dist-info/METADATA
ezwifi-1.0.0.11.dist-info/WHEEL
ezwifi-1.0.0.11.dist-info/top_level.txt
ezwifi-1.0.0.11.dist-info/RECORD
